buildfile/build.py
src/__init__.py
src/brain/__init__.py
src/brain/logic/__init__.py
src/brain/logic/logic.py
src/brain/logic/logicTest.py
src/brain/logic/read.py
src/brain/memory/__init__.py
src/brain/memory/longterm/__init__.py
src/brain/memory/longterm/load.py
src/brain/memory/longterm/write.py
src/brain/memory/shortterm/__init__.py
src/brain/tools/__init__.py
mojave-0.10.81.dist-info/METADATA
mojave-0.10.81.dist-info/WHEEL
mojave-0.10.81.dist-info/licenses/LICENSE
mojave-0.10.81.dist-info/RECORD
