Metadata-Version: 2.1
Name: mojave
Version: 0.10.81
Summary: Tooig Operating System
Project-URL: Homepage, https://github.com/tooig/mojave
Project-URL: Bug Tracker, https://github.com/tooig/mojave/issues
Author-email: "Tooig, Inc" <tooighq@gmail.com>, Oyebamijo <gloryoyebamijo@gmail.com>
License-File: LICENSE
Classifier: License :: OSI Approved :: MIT License
Classifier: Operating System :: OS Independent
Classifier: Programming Language :: Python :: 3
Requires-Python: >=3.8
